cfpq_data/__init__.py
cfpq_data/config.py
cfpq_data/dataset/__init__.py
cfpq_data/dataset/data.py
cfpq_data/grammars/__init__.py
cfpq_data/grammars/converters/__init__.py
cfpq_data/grammars/converters/cfg.py
cfpq_data/grammars/converters/cnf.py
cfpq_data/grammars/generators/__init__.py
cfpq_data/grammars/generators/c_alias_grammar.py
cfpq_data/grammars/generators/dyck_grammar.py
cfpq_data/grammars/generators/java_points_to_grammar.py
cfpq_data/grammars/generators/nested_parentheses_grammar.py
cfpq_data/grammars/readwrite/__init__.py
cfpq_data/grammars/readwrite/cfg.py
cfpq_data/grammars/readwrite/cnf.py
cfpq_data/grammars/readwrite/regex.py
cfpq_data/grammars/readwrite/rsa.py
cfpq_data/grammars/utils/__init__.py
cfpq_data/grammars/utils/change_terminals.py
cfpq_data/graphs/__init__.py
cfpq_data/graphs/generators/__init__.py
cfpq_data/graphs/generators/fast_labeled_binomial_graph.py
cfpq_data/graphs/generators/labeled_barabasi_albert_graph.py
cfpq_data/graphs/generators/labeled_binomial_graph.py
cfpq_data/graphs/generators/labeled_cycle_graph.py
cfpq_data/graphs/generators/labeled_scale_free_graph.py
cfpq_data/graphs/generators/labeled_two_cycles_graph.py
cfpq_data/graphs/readwrite/__init__.py
cfpq_data/graphs/readwrite/csv.py
cfpq_data/graphs/readwrite/rdf.py
cfpq_data/graphs/readwrite/txt.py
cfpq_data/graphs/utils/__init__.py
cfpq_data/graphs/utils/add_reverse_edges.py
cfpq_data/graphs/utils/change_edges.py
cfpq_data/graphs/utils/edges_statistics.py
cfpq_data/graphs/utils/filter_edges.py
cfpq_data/graphs/utils/multiple_source_utils.py
cfpq_data/graphs/utils/nodes_to_integers.py
cfpq_data-4.0.3.dist-info/LICENSE.txt
cfpq_data-4.0.3.dist-info/METADATA
cfpq_data-4.0.3.dist-info/WHEEL
cfpq_data-4.0.3.dist-info/top_level.txt
cfpq_data-4.0.3.dist-info/RECORD
