Metadata-Version: 2.1
Name: cfpq_data
Version: 4.0.3
Summary: Python package containing Graphs and Grammars for experimental analysis of Context-Free Path Querying algorithms
Home-page: https://formallanguageconstrainedpathquerying.github.io/CFPQ_Data/
Author: Vadim Abzalov
Author-email: vadim.i.abzalov@gmail.com
Maintainer: Nikita Kovalev
Maintainer-email: Nikitoskova123@gmail.com
Project-URL: Documentation, https://formallanguageconstrainedpathquerying.github.io/CFPQ_Data
Project-URL: Source Code, https://github.com/FormalLanguageConstrainedPathQuerying/CFPQ_Data
Project-URL: Bug Tracker, https://github.com/FormalLanguageConstrainedPathQuerying/CFPQ_Data/issues
Keywords: graphs,grammars,context-free,path-query,cfpq-data
Platform: Linux
Platform: Mac OSX
Platform: Unix
Platform: Windows
Classifier: Development Status :: 5 - Production/Stable
Classifier: Intended Audience :: Developers
Classifier: Intended Audience :: Science/Research
Classifier: Intended Audience :: Education
Classifier: License :: OSI Approved :: Apache Software License
Classifier: Operating System :: POSIX :: Linux
Classifier: Operating System :: MacOS
Classifier: Operating System :: Unix
Classifier: Operating System :: Microsoft :: Windows
Classifier: Operating System :: OS Independent
Classifier: Programming Language :: Python :: 3.9
Classifier: Programming Language :: Python :: 3 :: Only
Classifier: Topic :: Software Development :: Libraries :: Python Modules
Classifier: Topic :: Scientific/Engineering :: Bio-Informatics
Classifier: Topic :: Scientific/Engineering :: Information Analysis
Requires-Python: >=3.8
License-File: LICENSE.txt
Requires-Dist: networkx ==3.2.1
Requires-Dist: pandas ==2.2.1
Requires-Dist: pyformlang ==1.0.7
Requires-Dist: rdflib ==7.0.0
Requires-Dist: requests ==2.31.0
Provides-Extra: developer
Requires-Dist: black ==24.2.0 ; extra == 'developer'
Requires-Dist: pre-commit ==3.6.2 ; extra == 'developer'
Requires-Dist: pytest ==8.0.1 ; extra == 'developer'
Provides-Extra: docs
Requires-Dist: nb2plots ==0.7.2 ; extra == 'docs'
Requires-Dist: numpydoc ==1.6.0 ; extra == 'docs'
Requires-Dist: pydata-sphinx-theme ==0.15.2 ; extra == 'docs'
Requires-Dist: sphinx ==7.2.6 ; extra == 'docs'
Requires-Dist: sphinx-copybutton ==0.5.2 ; extra == 'docs'
Provides-Extra: tests
Requires-Dist: codecov >=2.1 ; extra == 'tests'
Requires-Dist: pytest >=6.2 ; extra == 'tests'
Requires-Dist: pytest-cov >=2.10 ; extra == 'tests'
